{"cameraMode":{"drawMode":0,"name":"Shaded","section":"Shading Mode"},"sceneLighting":false,"audioPlay":false,"sceneViewState":{"m_AlwaysRefresh":false,"showFog":true,"showSkybox":false,"showFlares":true,"showImageEffects":true,"showParticleSystems":true,"showVisualEffectGraphs":true,"m_FxEnabled":true},"in2DMode":false,"pivot":{"x":0.43681296706199648,"y":1.1548435688018799,"z":-0.04351634532213211},"rotation":{"x":-0.06414073705673218,"y":0.9264381527900696,"z":-0.18472318351268769,"w":-0.32167890667915347},"size":2.3241631984710695,"orthographic":false}